easylogz/__init__.py
easylogz/logger_module.py
easylogz-0.1.2.dist-info/licenses/LICENSE
easylogz-0.1.2.dist-info/METADATA
easylogz-0.1.2.dist-info/WHEEL
easylogz-0.1.2.dist-info/top_level.txt
easylogz-0.1.2.dist-info/RECORD
