Metadata-Version: 2.4
Name: easylogz
Version: 0.1.2
Summary: 一个简单易用的Python日志工具，提供开箱即用的日志管理功能
Author-email: zhong <2629144335@qq.com>
License: MIT
Project-URL: Homepage, https://github.com/z5013/EasyLog
Project-URL: Bug Tracker, https://github.com/z5013/EasyLog/issues
Project-URL: Source Code, https://github.com/z5013/EasyLog
Classifier: Programming Language :: Python :: 3
Classifier: Programming Language :: Python :: 3.8
Classifier: Programming Language :: Python :: 3.9
Classifier: Programming Language :: Python :: 3.10
Classifier: Programming Language :: Python :: 3.11
Classifier: License :: OSI Approved :: MIT License
Classifier: Operating System :: OS Independent
Classifier: Intended Audience :: Developers
Classifier: Topic :: Software Development :: Libraries :: Python Modules
Classifier: Topic :: System :: Logging
Requires-Python: >=3.8
License-File: LICENSE
Dynamic: license-file
